nonebot_plugin_jd_sign/__init__.py
nonebot_plugin_jd_sign/data_store.py
nonebot_plugin_jd_sign/handlers.py
nonebot_plugin_jd_sign/sign_jd.py
nonebot_plugin_jd_sign-0.1.6.dist-info/LICENSE.txt
nonebot_plugin_jd_sign-0.1.6.dist-info/METADATA
nonebot_plugin_jd_sign-0.1.6.dist-info/WHEEL
nonebot_plugin_jd_sign-0.1.6.dist-info/RECORD
