Metadata-Version: 2.1
Name: nonebot-plugin-jd-sign
Version: 0.1.6
Summary: 京东签到插件，支持京东cookies登录、自动签到、查询等功能
Home-page: https://github.com/Darker718/nonebot_plugin_jd_sign
License: MIT
Keywords: nonebot,plugin,京东,签到
Author: Darker718
Requires-Python: >=3.8,<4.0
Classifier: License :: OSI Approved :: MIT License
Classifier: Programming Language :: Python :: 3
Classifier: Programming Language :: Python :: 3.8
Classifier: Programming Language :: Python :: 3.9
Classifier: Programming Language :: Python :: 3.10
Classifier: Programming Language :: Python :: 3.11
Classifier: Programming Language :: Python :: 3.12
Classifier: Programming Language :: Python :: 3.13
Requires-Dist: httpx (>=0.27.2,<0.28.0)
Requires-Dist: loguru (>=0.7.2,<0.8.0)
Requires-Dist: nonebot-adapter-onebot (>=2.4.4,<3.0.0)
Requires-Dist: nonebot-plugin-apscheduler (>=0.5.0,<0.6.0)
Requires-Dist: nonebot2 (>=2.3.3,<3.0.0)
Project-URL: Repository, https://github.com/Darker718/nonebot_plugin_jd_sign
